rubypass.py
rubypass-0.2.5.1.dist-info/LICENSE
rubypass-0.2.5.1.dist-info/METADATA
rubypass-0.2.5.1.dist-info/WHEEL
rubypass-0.2.5.1.dist-info/top_level.txt
rubypass-0.2.5.1.dist-info/RECORD
