Metadata-Version: 2.1
Name: rubypass
Version: 0.2.5.1
Summary: A package made to extract video urls from 2 russian websites
Home-page: https://github.com/okawo80085/rubypass
Author: okawo
Author-email: okawo.198@gmail.com
License: UNKNOWN
Platform: UNKNOWN
Classifier: Programming Language :: Python :: 3
Classifier: Programming Language :: Python :: 3.6
Classifier: License :: OSI Approved :: MIT License
Classifier: Operating System :: OS Independent
Requires-Python: >=3
Requires-Dist: selenium
